pyswallow/__init__.py
pyswallow/constraints/__init__.py
pyswallow/constraints/base_constraints.py
pyswallow/constraints/constraint_manager.py
pyswallow/handlers/__init__.py
pyswallow/handlers/archive.py
pyswallow/handlers/base_handler.py
pyswallow/handlers/boundary_handler.py
pyswallow/handlers/inertia_handler.py
pyswallow/handlers/velocity_handler.py
pyswallow/opt/__init__.py
pyswallow/opt/base_swarm.py
pyswallow/opt/mopso.py
pyswallow/opt/sopso.py
pyswallow/swallows/__init__.py
pyswallow/swallows/base_swallow.py
pyswallow/swallows/mo_swallow.py
pyswallow/swallows/so_swallow.py
pyswallow/utils/__init__.py
pyswallow/utils/history.py
pyswallow/utils/reporter.py
pyswallow/utils/termination_manager.py
pyswallow/utils/functions/__init__.py
pyswallow/utils/functions/multi_objective.py
pyswallow/utils/functions/single_objective.py
pyswallow/utils/plotting/__init__.py
pyswallow/utils/plotting/plot_designer.py
pyswallow/utils/plotting/plotting.py
tests/constraints/__init__.py
tests/constraints/test_constraint_manager.py
tests/handlers/__init__.py
tests/handlers/test_archive.py
tests/handlers/test_boundary_handler.py
tests/handlers/test_inertia_handler.py
tests/handlers/test_velocity_handler.py
tests/opt/__init__.py
tests/opt/test_mopso.py
tests/opt/test_sopso.py
tests/swallows/__init__.py
tests/swallows/test_mo_swallow.py
tests/swallows/test_so_swallow.py
tests/utils/__init__.py
tests/utils/test_history.py
tests/utils/test_termination_manager.py
tests/utils/functions/__init__.py
tests/utils/functions/test_single_objective.py
PySwallow-1.0.0.dist-info/LICENSE.txt
PySwallow-1.0.0.dist-info/METADATA
PySwallow-1.0.0.dist-info/WHEEL
PySwallow-1.0.0.dist-info/top_level.txt
PySwallow-1.0.0.dist-info/RECORD
