Metadata-Version: 2.1
Name: PySwallow
Version: 1.0.0
Summary: A Python Particle Swarm Optimisation Library.
Home-page: https://github.com/danielkelshaw/PySwallow
Author: Daniel Kelshaw
Author-email: daniel.j.kelshaw@gmail.com
License: MIT License
Platform: UNKNOWN
Requires-Dist: pytest (==5.4.1)
Requires-Dist: numpy (==1.18.0)
Requires-Dist: matplotlib (==3.1.2)
